notelist_cli/__init__.py
notelist_cli/__main__.py
notelist_cli/admin.py
notelist_cli/auth.py
notelist_cli/config.py
notelist_cli/note.py
notelist_cli/notebook.py
notelist_cli/search.py
notelist_cli/user.py
notelist_cli-0.3.0.dist-info/LICENSE
notelist_cli-0.3.0.dist-info/METADATA
notelist_cli-0.3.0.dist-info/WHEEL
notelist_cli-0.3.0.dist-info/entry_points.txt
notelist_cli-0.3.0.dist-info/top_level.txt
notelist_cli-0.3.0.dist-info/RECORD
