Metadata-Version: 2.1
Name: notelist-cli
Version: 0.3.0
Summary: Command line interface for the Notelist API
Home-page: https://github.com/jajimenez/notelist-cli
Author: Jose A. Jimenez
Author-email: jajimenezcarm@gmail.com
License: MIT
Platform: UNKNOWN
Classifier: Programming Language :: Python :: 3
Classifier: Operating System :: OS Independent
Classifier: License :: OSI Approved :: MIT License
Requires-Python: >=3.9.0
Requires-Dist: click (==8.0.3)
Requires-Dist: requests (==2.26.0)
Requires-Dist: userconf (==0.4.0)
